LICENSE
MANIFEST.in
README.rst
setup.py
nagaral26project1.egg-info/PKG-INFO
nagaral26project1.egg-info/SOURCES.txt
nagaral26project1.egg-info/dependency_links.txt
nagaral26project1.egg-info/top_level.txt
src/__init__.py
src/core.py
src/helpers.py