Metadata-Version: 1.0
Name: nagaral26project1
Version: 0.1.1
Summary: Sample package for Python-Guide.org
Home-page: https://github.com/nagarwal26/project1
Author: Nitesh Agarwal
Author-email: UNKNOWN
License: Copyright (c) 2021, Nitesh Agarwal
